gronckle/__init__.py
gronckle/main.py
gronckle/rag/smart_chunking/demo_streamlit_app.py
gronckle/rag/smart_chunking/main.py
gronckle/rag/smart_chunking/split_text_responsibly.py
gronckle/rag/smart_chunking/text_splitter_prompt.py
gronckle-0.0.3.dist-info/LICENSE
gronckle-0.0.3.dist-info/METADATA
gronckle-0.0.3.dist-info/WHEEL
gronckle-0.0.3.dist-info/top_level.txt
gronckle-0.0.3.dist-info/RECORD
