Metadata-Version: 2.1
Name: gronckle
Version: 0.0.3
Summary: Quality of content LLM application infrastructure
Author-email: Griffin Clark <griffin@lionsentry.com>
Project-URL: Homepage, https://pypi.org/project/gronckle/
Project-URL: Issues, https://github.com/pypa/sampleproject/issues
Classifier: Programming Language :: Python :: 3
Classifier: License :: OSI Approved :: MIT License
Classifier: Operating System :: OS Independent
Requires-Python: >=3.8
License-File: LICENSE
